facade_edit_file_json/__init__.py
facade_edit_file_json/cli.py
facade_edit_file_json-0.1.4.dist-info/LICENSE
facade_edit_file_json-0.1.4.dist-info/METADATA
facade_edit_file_json-0.1.4.dist-info/WHEEL
facade_edit_file_json-0.1.4.dist-info/top_level.txt
facade_edit_file_json-0.1.4.dist-info/RECORD
