Metadata-Version: 2.1
Name: facade-edit-file-json
Version: 0.1.4
Summary: ...
Home-page: https://github.com/RivalStorms/facade-edit-file-json
Author: Tyshko Stanislav
Author-email: admin@toqp.ru
License: UNKNOWN
Platform: UNKNOWN
Classifier: License :: OSI Approved :: MIT License
